__init__.py
__main__.py
aur_check.py
base.py
capk.py
cd.py
config_find.py
ctnp.py
custom_commands.py
main.py
troubleshooting.py
crust_shell-0.1.3.dist-info/licenses/LICENSE
work/x86_64/airootfs/bin/event_rpcgen.py
work/x86_64/airootfs/bin/lsusb.py
work/x86_64/airootfs/lib/grub/i386-efi/gdb_helper.py
work/x86_64/airootfs/lib/grub/i386-pc/gdb_helper.py
work/x86_64/airootfs/lib/grub/x86_64-efi/gdb_helper.py
work/x86_64/airootfs/lib/openconnect/tncc-emulate.py
work/x86_64/airootfs/lib/openconnect/tncc-wrapper.py
work/x86_64/airootfs/lib64/grub/i386-efi/gdb_helper.py
work/x86_64/airootfs/lib64/grub/i386-pc/gdb_helper.py
work/x86_64/airootfs/lib64/grub/x86_64-efi/gdb_helper.py
work/x86_64/airootfs/lib64/openconnect/tncc-emulate.py
work/x86_64/airootfs/lib64/openconnect/tncc-wrapper.py
work/x86_64/airootfs/sbin/event_rpcgen.py
work/x86_64/airootfs/sbin/lsusb.py
work/x86_64/airootfs/usr/bin/event_rpcgen.py
work/x86_64/airootfs/usr/bin/lsusb.py
work/x86_64/airootfs/usr/lib/grub/i386-efi/gdb_helper.py
work/x86_64/airootfs/usr/lib/grub/i386-pc/gdb_helper.py
work/x86_64/airootfs/usr/lib/grub/x86_64-efi/gdb_helper.py
work/x86_64/airootfs/usr/lib/openconnect/tncc-emulate.py
work/x86_64/airootfs/usr/lib/openconnect/tncc-wrapper.py
work/x86_64/airootfs/usr/lib64/grub/i386-efi/gdb_helper.py
work/x86_64/airootfs/usr/lib64/grub/i386-pc/gdb_helper.py
work/x86_64/airootfs/usr/lib64/grub/x86_64-efi/gdb_helper.py
work/x86_64/airootfs/usr/lib64/openconnect/tncc-emulate.py
work/x86_64/airootfs/usr/lib64/openconnect/tncc-wrapper.py
work/x86_64/airootfs/usr/sbin/event_rpcgen.py
work/x86_64/airootfs/usr/sbin/lsusb.py
work/x86_64/airootfs/usr/share/openvpn/contrib/cmake/git-version.py
work/x86_64/airootfs/usr/share/openvpn/contrib/cmake/parse-version.m4.py
work/x86_64/airootfs/usr/share/openvpn/contrib/extract-crl/extractcrl.py
work/x86_64/airootfs/usr/share/vim/vim91/tools/demoserver.py
crust_shell-0.1.3.dist-info/METADATA
crust_shell-0.1.3.dist-info/WHEEL
crust_shell-0.1.3.dist-info/entry_points.txt
crust_shell-0.1.3.dist-info/top_level.txt
crust_shell-0.1.3.dist-info/RECORD
