Metadata-Version: 2.4
Name: crust-shell
Version: 0.1.3
Summary: Crust – a Python-based Linux shell with aliases and more.
Author: Juraj Kollár
Requires-Python: >=3.8
License-File: LICENSE
Requires-Dist: rich
Requires-Dist: requests
Requires-Dist: cohere
Dynamic: license-file
